bedevere/__init__.py
bedevere/constants.py
bedevere/discrete_sums.py
bedevere/dnd.py
bedevere/exceptions.py
bedevere/markov.py
bedevere/matrix.py
bedevere-0.1.1.dist-info/LICENSE
bedevere-0.1.1.dist-info/METADATA
bedevere-0.1.1.dist-info/WHEEL
bedevere-0.1.1.dist-info/top_level.txt
bedevere-0.1.1.dist-info/RECORD
