Metadata-Version: 2.1
Name: bedevere
Version: 0.1.1
Summary: A collection of useful mathematical functions for my other projects
Home-page: https://github.com/noahgill409/bedevere
Author: noahgill409
Author-email: noahgill409@gmail.com
License: MIT
Platform: UNKNOWN
Classifier: License :: OSI Approved :: MIT License
Classifier: Programming Language :: Python :: 3
Classifier: Programming Language :: Python :: 3.8
